baccoemu/__init__.py
baccoemu/_version.py
baccoemu/baryonic_boost.py
baccoemu/lbias_expansion.py
baccoemu/lbias_expansion_RSD.py
baccoemu/matter_bispectrum.py
baccoemu/matter_powerspectrum.py
baccoemu/utils.py
baccoemu-2.3.0.dist-info/licenses/AUTHORS.rst
baccoemu-2.3.0.dist-info/licenses/LICENSE
baccoemu-2.3.0.dist-info/METADATA
baccoemu-2.3.0.dist-info/WHEEL
baccoemu-2.3.0.dist-info/top_level.txt
baccoemu-2.3.0.dist-info/RECORD
