Metadata-Version: 2.4
Name: baccoemu
Version: 2.3.0
Summary: A collection of cosmological emulators for large-scale structure statistics
Home-page: http://dipc.org/bacco/
Author: Raul E Angulo, Giovanni Arico, Matteo Zennaro
Author-email: Raul E Angulo <reangulo@dipc.org>, Giovanni Arico <arico@bo.infn.it>, Matteo Zennaro <mzennaro@ice.csic.es>
License-Expression: MIT
Project-URL: Documentation, https://baccoemu.readthedocs.io/
Project-URL: Source, https://bitbucket.org/rangulo/baccoemu/
Project-URL: Tracker, https://bitbucket.org/rangulo/baccoemu/issues
Requires-Python: >=3.9
License-File: LICENSE
License-File: AUTHORS.rst
Requires-Dist: numpy
Requires-Dist: matplotlib
Requires-Dist: scipy
Requires-Dist: packaging
Requires-Dist: jax
Requires-Dist: h5py
Requires-Dist: setuptools
Requires-Dist: progressbar2
Requires-Dist: pytest
Requires-Dist: sphinx_rtd_theme
Provides-Extra: dev
Requires-Dist: black; extra == "dev"
Requires-Dist: flake8; extra == "dev"
Dynamic: author
Dynamic: home-page
Dynamic: license-file
Dynamic: requires-python
